<?xml version="1.0"?>

<PropertyList>

	<name>armament-panel</name>
	<path>A-10-armament-panel.ac</path>
	
	<animation>
		<object-name>master-arm-switch</object-name>
		<type>rotate</type>
		<property>sim/model/A-10/weapons/master-arm-switch</property>
		<factor>30</factor>
		<center>
			<x-m>0.0029</x-m>
			<y-m>0.0948</y-m>
			<z-m>0.0575</z-m>
		</center>
		<axis><y>-1</y></axis>
	</animation>

	<animation>
		<object-name>gun-rate-switch</object-name>
		<type>rotate</type>
		<property>sim/model/A-10/weapons/gun-rate-switch</property>
		<factor>30</factor>
		<center>
			<x-m>0.0031</x-m>
			<y-m>-0.0929</y-m>
			<z-m>0.0575</z-m>
		</center>
		<axis><y>-1</y></axis>
	</animation>

	<animation>
		<object-name>aim-9-knob</object-name>
		<type>rotate</type>
		<property>sim/model/A-10/weapons/dual-AIM-9/aim9-knob</property>
		<factor>45</factor>
		<center>
			<x-m>0.0031</x-m>
			<y-m>-0.0535</y-m>
			<z-m>-0.0628</z-m>
		</center>
		<axis><x>-1</x></axis>
	</animation>

	<animation>
		<type>select</type>
		<object-name>aim-9-light-on</object-name>
		<condition>
			<equals>
				<property>sim/model/A-10/weapons/aim-9/cooled</property>
				<value>2</value>
			</equals>
		</condition>
	</animation>


	<!--stations-->
	<!--station[0] only AN-ALQ-131 (error on select)-->
	<animation>
		<type>select</type>
		<object-name>s-0-0</object-name>
		<condition>
			<property>sim/model/A-10/weapons/master-arm-switch</property>
			<property>sim/model/A-10/weapons/stations/station[0]/ready-0</property>
			<property>sim/model/A-10/weapons/stations/station[0]/selected</property>
			<greater-than>
				<property>systems/electrical/R-AC-volts</property>
				<value>24</value>
			</greater-than>
		</condition>
	</animation>
	<animation>
		<type>select</type>
		<object-name>s-0-1</object-name>
		<condition>
			<property>sim/model/A-10/weapons/master-arm-switch</property>
			<property>sim/model/A-10/weapons/stations/station[0]/ready-1</property>
			<property>sim/model/A-10/weapons/stations/station[0]/selected</property>
			<greater-than>
				<property>systems/electrical/R-AC-volts</property>
				<value>24</value>
			</greater-than>
		</condition>
	</animation>
	<animation>
		<type>select</type>
		<object-name>s-0-2</object-name>
		<condition>
			<property>sim/model/A-10/weapons/master-arm-switch</property>
			<property>sim/model/A-10/weapons/stations/station[0]/ready-2</property>
			<property>sim/model/A-10/weapons/stations/station[0]/selected</property>
			<greater-than>
				<property>systems/electrical/R-AC-volts</property>
				<value>24</value>
			</greater-than>
		</condition>
	</animation>
	<animation>
		<type>select</type>
		<object-name>s-0-E</object-name>
		<condition>
			<property>sim/model/A-10/weapons/master-arm-switch</property>
			<property>sim/model/A-10/weapons/stations/station[0]/error</property>
			<property>sim/model/A-10/weapons/stations/station[0]/selected</property>
			<greater-than>
				<property>systems/electrical/R-AC-volts</property>
				<value>24</value>
			</greater-than>
		</condition>
	</animation>

	<!--station[1] -->
	<animation>
		<type>select</type>
		<object-name>s-1-0</object-name>
		<condition>
			<property>sim/model/A-10/weapons/master-arm-switch</property>
			<property>sim/model/A-10/weapons/stations/station[1]/ready-0</property>
			<property>sim/model/A-10/weapons/stations/station[1]/selected</property>
			<greater-than>
				<property>systems/electrical/R-AC-volts</property>
				<value>24</value>
			</greater-than>
		</condition>
	</animation>
	<animation>
		<type>select</type>
		<object-name>s-1-1</object-name>
		<condition>
			<property>sim/model/A-10/weapons/master-arm-switch</property>
			<property>sim/model/A-10/weapons/stations/station[1]/ready-1</property>
			<property>sim/model/A-10/weapons/stations/station[1]/selected</property>
			<greater-than>
				<property>systems/electrical/R-AC-volts</property>
				<value>24</value>
			</greater-than>
		</condition>
	</animation>
	<animation>
		<type>select</type>
		<object-name>s-1-2</object-name>
		<condition>
			<property>sim/model/A-10/weapons/master-arm-switch</property>
			<property>sim/model/A-10/weapons/stations/station[1]/ready-2</property>
			<property>sim/model/A-10/weapons/stations/station[1]/selected</property>
			<greater-than>
				<property>systems/electrical/R-AC-volts</property>
				<value>24</value>
			</greater-than>
		</condition>
	</animation>
	<animation>
		<type>select</type>
		<object-name>s-1-E</object-name>
		<condition>
			<property>sim/model/A-10/weapons/master-arm-switch</property>
			<property>sim/model/A-10/weapons/stations/station[1]/error</property>
			<property>sim/model/A-10/weapons/stations/station[1]/selected</property>
			<greater-than>
				<property>systems/electrical/R-AC-volts</property>
				<value>24</value>
			</greater-than>
		</condition>
	</animation>

	<!--station[2] -->
	<animation>
		<type>select</type>
		<object-name>s-2-0</object-name>
		<condition>
			<property>sim/model/A-10/weapons/master-arm-switch</property>
			<property>sim/model/A-10/weapons/stations/station[2]/ready-0</property>
			<property>sim/model/A-10/weapons/stations/station[2]/selected</property>
			<greater-than>
				<property>systems/electrical/R-AC-volts</property>
				<value>24</value>
			</greater-than>
		</condition>
	</animation>
	<animation>
		<type>select</type>
		<object-name>s-2-1</object-name>
		<condition>
			<property>sim/model/A-10/weapons/master-arm-switch</property>
			<property>sim/model/A-10/weapons/stations/station[2]/ready-1</property>
			<property>sim/model/A-10/weapons/stations/station[2]/selected</property>
			<greater-than>
				<property>systems/electrical/R-AC-volts</property>
				<value>24</value>
			</greater-than>
		</condition>
	</animation>
	<animation>
		<type>select</type>
		<object-name>s-2-2</object-name>
		<condition>
			<property>sim/model/A-10/weapons/master-arm-switch</property>
			<property>sim/model/A-10/weapons/stations/station[2]/ready-2</property>
			<property>sim/model/A-10/weapons/stations/station[2]/selected</property>
			<greater-than>
				<property>systems/electrical/R-AC-volts</property>
				<value>24</value>
			</greater-than>
		</condition>
	</animation>
	<animation>
		<type>select</type>
		<object-name>s-2-E</object-name>
		<condition>
			<property>sim/model/A-10/weapons/master-arm-switch</property>
			<property>sim/model/A-10/weapons/stations/station[2]/error</property>
			<property>sim/model/A-10/weapons/stations/station[2]/selected</property>
			<greater-than>
				<property>systems/electrical/R-AC-volts</property>
				<value>24</value>
			</greater-than>
		</condition>
	</animation>

	<!--station[3] -->
	<animation>
		<type>select</type>
		<object-name>s-3-0</object-name>
		<condition>
			<property>sim/model/A-10/weapons/master-arm-switch</property>
			<property>sim/model/A-10/weapons/stations/station[3]/ready-0</property>
			<property>sim/model/A-10/weapons/stations/station[3]/selected</property>
			<greater-than>
				<property>systems/electrical/R-AC-volts</property>
				<value>24</value>
			</greater-than>
		</condition>
	</animation>
	<animation>
		<type>select</type>
		<object-name>s-3-1</object-name>
		<condition>
			<property>sim/model/A-10/weapons/master-arm-switch</property>
			<property>sim/model/A-10/weapons/stations/station[3]/ready-1</property>
			<property>sim/model/A-10/weapons/stations/station[3]/selected</property>
			<greater-than>
				<property>systems/electrical/R-AC-volts</property>
				<value>24</value>
			</greater-than>
		</condition>
	</animation>
	<animation>
		<type>select</type>
		<object-name>s-3-2</object-name>
		<condition>
			<property>sim/model/A-10/weapons/master-arm-switch</property>
			<property>sim/model/A-10/weapons/stations/station[3]/ready-2</property>
			<property>sim/model/A-10/weapons/stations/station[3]/selected</property>
			<greater-than>
				<property>systems/electrical/R-AC-volts</property>
				<value>24</value>
			</greater-than>
		</condition>
	</animation>
	<animation>
		<type>select</type>
		<object-name>s-3-E</object-name>
		<condition>
			<property>sim/model/A-10/weapons/master-arm-switch</property>
			<property>sim/model/A-10/weapons/stations/station[3]/error</property>
			<property>sim/model/A-10/weapons/stations/station[3]/selected</property>
			<greater-than>
				<property>systems/electrical/R-AC-volts</property>
				<value>24</value>
			</greater-than>
		</condition>
	</animation>

	<!--station[4] -->
	<animation>
		<type>select</type>
		<object-name>s-4-0</object-name>
		<condition>
			<property>sim/model/A-10/weapons/master-arm-switch</property>
			<property>sim/model/A-10/weapons/stations/station[4]/ready-0</property>
			<property>sim/model/A-10/weapons/stations/station[4]/selected</property>
			<greater-than>
				<property>systems/electrical/R-AC-volts</property>
				<value>24</value>
			</greater-than>
		</condition>
	</animation>
	<animation>
		<type>select</type>
		<object-name>s-4-1</object-name>
		<condition>
			<property>sim/model/A-10/weapons/master-arm-switch</property>
			<property>sim/model/A-10/weapons/stations/station[4]/ready-1</property>
			<property>sim/model/A-10/weapons/stations/station[4]/selected</property>
			<greater-than>
				<property>systems/electrical/R-AC-volts</property>
				<value>24</value>
			</greater-than>
		</condition>
	</animation>
	<animation>
		<type>select</type>
		<object-name>s-4-2</object-name>
		<condition>
			<property>sim/model/A-10/weapons/master-arm-switch</property>
			<property>sim/model/A-10/weapons/stations/station[4]/ready-2</property>
			<property>sim/model/A-10/weapons/stations/station[4]/selected</property>
			<greater-than>
				<property>systems/electrical/R-AC-volts</property>
				<value>24</value>
			</greater-than>
		</condition>
	</animation>
	<animation>
		<type>select</type>
		<object-name>s-4-E</object-name>
		<condition>
			<property>sim/model/A-10/weapons/master-arm-switch</property>
			<property>sim/model/A-10/weapons/stations/station[4]/error</property>
			<property>sim/model/A-10/weapons/stations/station[4]/selected</property>
			<greater-than>
				<property>systems/electrical/R-AC-volts</property>
				<value>24</value>
			</greater-than>
		</condition>
	</animation>

	<!--station[5] -->
	<animation>
		<type>select</type>
		<object-name>s-5-0</object-name>
		<condition>
			<property>sim/model/A-10/weapons/master-arm-switch</property>
			<property>sim/model/A-10/weapons/stations/station[5]/ready-0</property>
			<property>sim/model/A-10/weapons/stations/station[5]/selected</property>
			<greater-than>
				<property>systems/electrical/R-AC-volts</property>
				<value>24</value>
			</greater-than>
		</condition>
	</animation>
	<animation>
		<type>select</type>
		<object-name>s-5-1</object-name>
		<condition>
			<property>sim/model/A-10/weapons/master-arm-switch</property>
			<property>sim/model/A-10/weapons/stations/station[5]/ready-1</property>
			<property>sim/model/A-10/weapons/stations/station[5]/selected</property>
			<greater-than>
				<property>systems/electrical/R-AC-volts</property>
				<value>24</value>
			</greater-than>
		</condition>
	</animation>
	<animation>
		<type>select</type>
		<object-name>s-5-2</object-name>
		<condition>
			<property>sim/model/A-10/weapons/master-arm-switch</property>
			<property>sim/model/A-10/weapons/stations/station[5]/ready-2</property>
			<property>sim/model/A-10/weapons/stations/station[5]/selected</property>
			<greater-than>
				<property>systems/electrical/R-AC-volts</property>
				<value>24</value>
			</greater-than>
		</condition>
	</animation>
	<animation>
		<type>select</type>
		<object-name>s-5-E</object-name>
		<condition>
			<property>sim/model/A-10/weapons/master-arm-switch</property>
			<property>sim/model/A-10/weapons/stations/station[5]/error</property>
			<property>sim/model/A-10/weapons/stations/station[5]/selected</property>
			<greater-than>
				<property>systems/electrical/R-AC-volts</property>
				<value>24</value>
			</greater-than>
		</condition>
	</animation>

	<!--station[6] -->
	<animation>
		<type>select</type>
		<object-name>s-6-0</object-name>
		<condition>
			<property>sim/model/A-10/weapons/master-arm-switch</property>
			<property>sim/model/A-10/weapons/stations/station[6]/ready-0</property>
			<property>sim/model/A-10/weapons/stations/station[6]/selected</property>
			<greater-than>
				<property>systems/electrical/R-AC-volts</property>
				<value>24</value>
			</greater-than>
		</condition>
	</animation>
	<animation>
		<type>select</type>
		<object-name>s-6-1</object-name>
		<condition>
			<property>sim/model/A-10/weapons/master-arm-switch</property>
			<property>sim/model/A-10/weapons/stations/station[6]/ready-1</property>
			<property>sim/model/A-10/weapons/stations/station[6]/selected</property>
			<greater-than>
				<property>systems/electrical/R-AC-volts</property>
				<value>24</value>
			</greater-than>
		</condition>
	</animation>
	<animation>
		<type>select</type>
		<object-name>s-6-2</object-name>
		<condition>
			<property>sim/model/A-10/weapons/master-arm-switch</property>
			<property>sim/model/A-10/weapons/stations/station[6]/ready-2</property>
			<property>sim/model/A-10/weapons/stations/station[6]/selected</property>
			<greater-than>
				<property>systems/electrical/R-AC-volts</property>
				<value>24</value>
			</greater-than>
		</condition>
	</animation>
	<animation>
		<type>select</type>
		<object-name>s-6-E</object-name>
		<condition>
			<property>sim/model/A-10/weapons/master-arm-switch</property>
			<property>sim/model/A-10/weapons/stations/station[6]/error</property>
			<property>sim/model/A-10/weapons/stations/station[6]/selected</property>
			<greater-than>
				<property>systems/electrical/R-AC-volts</property>
				<value>24</value>
			</greater-than>
		</condition>
	</animation>

	<!--station[7] -->
	<animation>
		<type>select</type>
		<object-name>s-7-0</object-name>
		<condition>
			<property>sim/model/A-10/weapons/master-arm-switch</property>
			<property>sim/model/A-10/weapons/stations/station[7]/ready-0</property>
			<property>sim/model/A-10/weapons/stations/station[7]/selected</property>
			<greater-than>
				<property>systems/electrical/R-AC-volts</property>
				<value>24</value>
			</greater-than>
		</condition>
	</animation>
	<animation>
		<type>select</type>
		<object-name>s-7-1</object-name>
		<condition>
			<property>sim/model/A-10/weapons/master-arm-switch</property>
			<property>sim/model/A-10/weapons/stations/station[7]/ready-1</property>
			<property>sim/model/A-10/weapons/stations/station[7]/selected</property>
			<greater-than>
				<property>systems/electrical/R-AC-volts</property>
				<value>24</value>
			</greater-than>
		</condition>
	</animation>
	<animation>
		<type>select</type>
		<object-name>s-7-2</object-name>
		<condition>
			<property>sim/model/A-10/weapons/master-arm-switch</property>
			<property>sim/model/A-10/weapons/stations/station[7]/ready-2</property>
			<property>sim/model/A-10/weapons/stations/station[7]/selected</property>
			<greater-than>
				<property>systems/electrical/R-AC-volts</property>
				<value>24</value>
			</greater-than>
		</condition>
	</animation>
	<animation>
		<type>select</type>
		<object-name>s-7-E</object-name>
		<condition>
			<property>sim/model/A-10/weapons/master-arm-switch</property>
			<property>sim/model/A-10/weapons/stations/station[7]/error</property>
			<property>sim/model/A-10/weapons/stations/station[7]/selected</property>
			<greater-than>
				<property>systems/electrical/R-AC-volts</property>
				<value>24</value>
			</greater-than>
		</condition>
	</animation>

	<!--station[8] -->
	<animation>
		<type>select</type>
		<object-name>s-8-0</object-name>
		<condition>
			<property>sim/model/A-10/weapons/master-arm-switch</property>
			<property>sim/model/A-10/weapons/stations/station[8]/ready-0</property>
			<property>sim/model/A-10/weapons/stations/station[8]/selected</property>
			<greater-than>
				<property>systems/electrical/R-AC-volts</property>
				<value>24</value>
			</greater-than>
		</condition>
	</animation>
	<animation>
		<type>select</type>
		<object-name>s-8-1</object-name>
		<condition>
			<property>sim/model/A-10/weapons/master-arm-switch</property>
			<property>sim/model/A-10/weapons/stations/station[8]/ready-1</property>
			<property>sim/model/A-10/weapons/stations/station[8]/selected</property>
			<greater-than>
				<property>systems/electrical/R-AC-volts</property>
				<value>24</value>
			</greater-than>
		</condition>
	</animation>
	<animation>
		<type>select</type>
		<object-name>s-8-2</object-name>
		<condition>
			<property>sim/model/A-10/weapons/master-arm-switch</property>
			<property>sim/model/A-10/weapons/stations/station[8]/ready-2</property>
			<property>sim/model/A-10/weapons/stations/station[8]/selected</property>
			<greater-than>
				<property>systems/electrical/R-AC-volts</property>
				<value>24</value>
			</greater-than>
		</condition>
	</animation>
	<animation>
		<type>select</type>
		<object-name>s-8-E</object-name>
		<condition>
			<property>sim/model/A-10/weapons/master-arm-switch</property>
			<property>sim/model/A-10/weapons/stations/station[8]/error</property>
			<property>sim/model/A-10/weapons/stations/station[8]/selected</property>
			<greater-than>
				<property>systems/electrical/R-AC-volts</property>
				<value>24</value>
			</greater-than>
		</condition>
	</animation>

	<!--station[9] -->
	<animation>
		<type>select</type>
		<object-name>s-9-0</object-name>
		<condition>
			<property>sim/model/A-10/weapons/master-arm-switch</property>
			<property>sim/model/A-10/weapons/stations/station[9]/ready-0</property>
			<property>sim/model/A-10/weapons/stations/station[9]/selected</property>
			<greater-than>
				<property>systems/electrical/R-AC-volts</property>
				<value>24</value>
			</greater-than>
		</condition>
	</animation>
	<animation>
		<type>select</type>
		<object-name>s-9-1</object-name>
		<condition>
			<property>sim/model/A-10/weapons/master-arm-switch</property>
			<property>sim/model/A-10/weapons/stations/station[9]/ready-1</property>
			<property>sim/model/A-10/weapons/stations/station[9]/selected</property>
			<greater-than>
				<property>systems/electrical/R-AC-volts</property>
				<value>24</value>
			</greater-than>
		</condition>
	</animation>
	<animation>
		<type>select</type>
		<object-name>s-9-2</object-name>
		<condition>
			<property>sim/model/A-10/weapons/master-arm-switch</property>
			<property>sim/model/A-10/weapons/stations/station[9]/ready-2</property>
			<property>sim/model/A-10/weapons/stations/station[9]/selected</property>
			<greater-than>
				<property>systems/electrical/R-AC-volts</property>
				<value>24</value>
			</greater-than>
		</condition>
	</animation>
	<animation>
		<type>select</type>
		<object-name>s-9-E</object-name>
		<condition>
			<property>sim/model/A-10/weapons/master-arm-switch</property>
			<property>sim/model/A-10/weapons/stations/station[9]/error</property>
			<property>sim/model/A-10/weapons/stations/station[9]/selected</property>
			<greater-than>
				<property>systems/electrical/R-AC-volts</property>
				<value>24</value>
			</greater-than>
		</condition>
	</animation>

	<!--station[10] only dual-AIM-9 -->
	<animation>
		<type>select</type>
		<object-name>s-10-0</object-name>
		<condition>
			<property>sim/model/A-10/weapons/master-arm-switch</property>
			<property>sim/model/A-10/weapons/stations/station[10]/ready-0</property>
			<property>sim/model/A-10/weapons/stations/station[10]/selected</property>
			<greater-than>
				<property>systems/electrical/R-AC-volts</property>
				<value>24</value>
			</greater-than>
		</condition>
	</animation>
	<animation>
		<type>select</type>
		<object-name>s-10-1</object-name>
		<condition>
			<property>sim/model/A-10/weapons/master-arm-switch</property>
			<property>sim/model/A-10/weapons/stations/station[10]/ready-1</property>
			<property>sim/model/A-10/weapons/stations/station[10]/selected</property>
			<greater-than>
				<property>systems/electrical/R-AC-volts</property>
				<value>24</value>
			</greater-than>
			</condition>
	</animation>
	<animation>
		<type>select</type>
		<object-name>s-10-2</object-name>
		<condition>
			<property>sim/model/A-10/weapons/master-arm-switch</property>
			<property>sim/model/A-10/weapons/stations/station[10]/ready-2</property>
			<property>sim/model/A-10/weapons/stations/station[10]/selected</property>
			<greater-than>
				<property>systems/electrical/R-AC-volts</property>
				<value>24</value>
			</greater-than>
		</condition>
	</animation>
	<animation>
		<type>select</type>
		<object-name>s-10-E</object-name>
		<condition>
			<property>sim/model/A-10/weapons/master-arm-switch</property>
			<property>sim/model/A-10/weapons/stations/station[10]/error</property>
			<property>sim/model/A-10/weapons/stations/station[10]/selected</property>
			<greater-than>
				<property>systems/electrical/R-AC-volts</property>
				<value>24</value>
			</greater-than>
		</condition>
	</animation>

	<!-- tests all w togather-->
	<!--<animation>
		<type>select</type>
		<object-name>lights</object-name>
		<condition>
			<property>sim/model/A-10/weapons/master-arm-switch</property>
			<property>sim/model/A-10/weapons/station-light-test</property>
			<greater-than>
				<property>systems/electrical/R-AC-volts</property>
				<value>24</value>
			</greater-than>
		</condition>
	</animation>-->

	<!--rnds counter-->
	<animation>
		<type>select</type>
		<object-name>rds-rem-x1</object-name>
		<condition>
			<greater-than>
				<property>systems/electrical/R-AC-volts</property>
				<value>24</value>
			</greater-than>
		</condition>
	</animation>
	
	<animation>
		<type>select</type>
		<object-name>rds-rem-x10</object-name>
		<condition>
			<greater-than>
				<property>systems/electrical/R-AC-volts</property>
				<value>24</value>
			</greater-than>
		</condition>
	</animation>
	
	<animation>
		<type>select</type>
		<object-name>rds-rem-x100</object-name>
		<condition>
			<greater-than>
				<property>systems/electrical/R-AC-volts</property>
				<value>24</value>
			</greater-than>
		</condition>
	</animation>
	
	<animation>
		<type>select</type>
		<object-name>rds-rem-x1000</object-name>
		<condition>
			<greater-than>
				<property>systems/electrical/R-AC-volts</property>
				<value>24</value>
			</greater-than>
		</condition>
	</animation>
	
	<animation>
		<type>textranslate</type>
		<object-name>rds-rem-x1</object-name>
		<property>ai/submodels/submodel[1]/count</property>
		<factor>0.1</factor>
		<axis><y>-1</y></axis>
	</animation>

	<animation>
		<type>textranslate</type>
		<object-name>rds-rem-x10</object-name>
		<property>ai/submodels/submodel[1]/count</property>
		<factor>0.01</factor>
		<step>10</step>
		<scroll>0.5</scroll>
		<axis><y>-1</y></axis>
	</animation>

	<animation>
		<type>textranslate</type>
		<object-name>rds-rem-x100</object-name>
		<property>ai/submodels/submodel[1]/count</property>
		<factor>0.001</factor>
		<step>100</step>
		<scroll>0.5</scroll>
		<axis><y>-1</y></axis>
	</animation>


	<animation>
		<type>textranslate</type>
		<object-name>rds-rem-x1000</object-name>
		<property>ai/submodels/submodel[1]/count</property>
		<factor>0.0001</factor>
		<step>1000</step>
		<scroll>0.5</scroll>
		<axis><y>-1</y></axis>
	</animation>

	<!--rip counter-->
	<animation>
		<type>textranslate</type>
		<object-name>rip-qty-x1</object-name>
		<property>sim/model/A-10/weapons/rip</property>
		<factor>0.1</factor>
		<axis><y>-1</y></axis>
	</animation>

	<animation>
		<type>textranslate</type>
		<object-name>rip-qty-x10</object-name>
		<property>sim/model/A-10/weapons/rip</property>
		<factor>0.01</factor>
		<step>10</step>
		<scroll>0.5</scroll>
		<axis><y>-1</y></axis>
	</animation>

	<!--interval counter-->
	<animation>
		<type>textranslate</type>
		<object-name>rip-intvl-x1</object-name>
		<property>sim/model/A-10/weapons/interval</property>
		<factor>10</factor>
		<axis><y>-1</y></axis>
	</animation>

	<animation>
		<type>textranslate</type>
		<object-name>rip-intvl-x10</object-name>
		<property>sim/model/A-10/weapons/interval</property>
		<factor>1</factor>
		<step>0.0999</step>
		<axis><y>-1</y></axis>
	</animation>


	<!-- lighting -->

	<!--switches and knobs-->
	<animation>
		<object-name>panel</object-name>
		<type>material</type>
		<emission>
			<factor-prop>controls/lighting/panel-norm</factor-prop>
			<red>0.385</red>
			<green>0.168</green>
			<blue>0.07</blue>
		</emission>
	</animation>


	<!--rds counter
	<animation>
		<object-name>rds</object-name>
		<type>material</type>
		<emission>
			<factor-prop>controls/lighting/instruments-norm</factor-prop>
			<red>0.55</red>
			<green>0.24</green>
			<blue>0.10</blue>
		</emission>
	</animation>-->


	<!-- rip counter-->
	<animation>
		<object-name>rip-qty</object-name>
		<type>material</type>
		<emission>
			<factor-prop>controls/lighting/instruments-norm</factor-prop>
			<red>0.55</red>
			<green>0.24</green>
			<blue>0.10</blue>
		</emission>
	</animation>



	<!--LOD-->
	<animation>
		<type>range</type>
		<min-m>0</min-m>
		<max-m>5</max-m>
	</animation>

</PropertyList>
